[
  {
    "name": "Alfa",
    "description": "Польша"
  },
  {
    "name": "Luminex",
    "description": "Польша"
  },
  {
    "name": "Kemar",
    "description": "Польша"
  },
  {
    "name": "Emibig",
    "description": "Польша"
  },
  {
    "name": "Jupiter",
    "description": "Польша"
  },
  {
    "name": "ADILUX",
    "description": "Дания"
  },
  {
    "name": "Freya",
    "description": "Германия"
  },
  {
    "name": "Maytoni",
    "description": "Германия"
  },
  {
    "name": "Technical",
    "description": "Германия"
  },
  {
    "name": "Voltega",
    "description": "Германия"
  },
  {
    "name": "Namat",
    "description": ""
  },
  {
    "name": "Outdoor",
    "description": "Германия"
  },
  {
    "name": "Nowodvorski",
    "description": "Польша"
  },
  {
    "name": "ST LUCE",
    "description": "Италия"
  },
  {
    "name": "EVOLUCE",
    "description": "Италия"
  },
  {
    "name": "EVOLED",
    "description": "Италия"
  },
  {
    "name": "MW-Light",
    "description": "Германия"
  },
  {
    "name": "CHIARO",
    "description": "Германия"
  },
  {
    "name": "De Markt",
    "description": "Германия"
  },
  {
    "name": "De City",
    "description": "Германия"
  },
  {
    "name": "Evronomer",
    "description": ""
  },
  {
    "name": "Vele Luce",
    "description": "Италия"
  },
  {
    "name": "Elektrostandard",
    "description": "Германия"
  },
  {
    "name": "Elektrostandard Pro",
    "description": "Германия"
  },
  {
    "name": "Werkel",
    "description": "Швеция"
  },
  {
    "name": "Eurosvet",
    "description": "Россия"
  },
  {
    "name": "TK Lighting",
    "description": "Польша"
  },
  {
    "name": "Bogate's",
    "description": "Россия"
  },
  {
    "name": "Lussole",
    "description": "Италия"
  }
]
